foxcross/__init__.py
foxcross/__version__.py
foxcross/constants.py
foxcross/endpoints.py
foxcross/enums.py
foxcross/exceptions.py
foxcross/pandas_serving.py
foxcross/runner.py
foxcross/serving.py
foxcross/templates/base.html
foxcross/templates/data_format_form.html
foxcross/templates/index.html
foxcross/templates/input_format.html
foxcross/templates/predict.html
foxcross/templates/predict_test.html
foxcross/templates.py
foxcross-0.10.0.dist-info/LICENSE.md
foxcross-0.10.0.dist-info/WHEEL
foxcross-0.10.0.dist-info/METADATA
foxcross-0.10.0.dist-info/RECORD
