Metadata-Version: 2.1
Name: foxcross
Version: 0.10.0
Summary: AsyncIO serving for data science models
Home-page: https://github.com/laactech/foxcross
License: BSD-3-Clause
Keywords: data science,machine learning,serving,python,async,dataframe,pandas,scikit-learn,pytorch,http,rest api
Author: Steven Pate
Author-email: steven@laac.dev
Requires-Python: >=3.6.1,<4.0.0
Classifier: Development Status :: 3 - Alpha
Classifier: Environment :: Web Environment
Classifier: Framework :: AsyncIO
Classifier: Intended Audience :: Developers
Classifier: Intended Audience :: Science/Research
Classifier: License :: OSI Approved :: BSD License
Classifier: Natural Language :: English
Classifier: Operating System :: OS Independent
Classifier: Programming Language :: Python
Classifier: Programming Language :: Python :: 3
Classifier: Programming Language :: Python :: 3.6
Classifier: Programming Language :: Python :: 3.7
Classifier: Programming Language :: Python :: 3.8
Classifier: Topic :: Internet :: WWW/HTTP
Provides-Extra: modin
Provides-Extra: pandas
Provides-Extra: ujson
Requires-Dist: aiofiles (>=0.5.0,<0.6.0)
Requires-Dist: jinja2 (>=2.10,<3.0)
Requires-Dist: modin (>=0.7.0,<0.8.0); extra == "modin"
Requires-Dist: pandas (>=1.0.0,<2.0.0); extra == "pandas"
Requires-Dist: python-slugify[unidecode] (>=4.0,<5.0)
Requires-Dist: starlette (>=0.13.0,<0.14.0)
Requires-Dist: ujson (>=2.0,<3.0); extra == "ujson"
Requires-Dist: uvicorn (>=0.11.0,<0.12.0)
Project-URL: Documentation, https://www.foxcross.dev/
Project-URL: Repository, https://github.com/laactech/foxcross
